setup.py
pakiet_testowy/__init__.py
pakiet_testowy/dodawanie.py
zdpytpol81.egg-info/PKG-INFO
zdpytpol81.egg-info/SOURCES.txt
zdpytpol81.egg-info/dependency_links.txt
zdpytpol81.egg-info/top_level.txt