Metadata-Version: 2.1
Name: zdpytpol81
Version: 0.0.2
Summary: some description
Home-page: UNKNOWN
Author: Ditto
License: UNKNOWN
Platform: UNKNOWN
